isssm/__init__.py
isssm/_modidx.py
isssm/ce_method.py
isssm/estimation.py
isssm/glssm.py
isssm/importance_sampling.py
isssm/kalman.py
isssm/laplace_approximation.py
isssm/models/__init__.py
isssm/models/glssm.py
isssm/models/pgssm.py
isssm/models/stsm.py
isssm/modified_efficient_importance_sampling.py
isssm/pgssm.py
isssm/typing.py
isssm/util.py
isssm-0.1.0.dist-info/WHEEL
isssm-0.1.0.dist-info/METADATA
isssm-0.1.0.dist-info/RECORD
