Metadata-Version: 2.3
Name: isssm
Version: 0.1.0
Summary: Importance Sampling for State Space Models (in jax)
Author: Stefan Heyder
Author-email: Stefan Heyder <stefan.heyder@gmail.com>
License: MIT
Classifier: Development Status :: 3 - Alpha
Classifier: Intended Audience :: Developers
Classifier: License :: OSI Approved :: MIT License
Classifier: Programming Language :: Python :: 3
Requires-Dist: jax[cpu]==0.6.1
Requires-Dist: jaxtyping>=0.3.2
Requires-Dist: numpy
Requires-Dist: scipy
Requires-Dist: tensorflow-probability>=0.25.0
Requires-Dist: jaxopt
Requires-Dist: jaxlib
Requires-Dist: setuptools>=80.9.0
Requires-Dist: matplotlib ; extra == 'dev'
Requires-Dist: nbdev ; extra == 'dev'
Requires-Dist: ipykernel ; extra == 'dev'
Requires-Python: >=3.10
Project-URL: Bug Tracker, https://github.com/stefanheyder/isssm/issues
Project-URL: Homepage, https://github.com/stefanheyder/isssm
Provides-Extra: dev
